setup.cfg
setup.py
python_slimta_cloudstorage.egg-info/PKG-INFO
python_slimta_cloudstorage.egg-info/SOURCES.txt
python_slimta_cloudstorage.egg-info/dependency_links.txt
python_slimta_cloudstorage.egg-info/namespace_packages.txt
python_slimta_cloudstorage.egg-info/requires.txt
python_slimta_cloudstorage.egg-info/top_level.txt
slimta/__init__.py
slimta/cloudstorage/__init__.py
slimta/cloudstorage/aws.py
slimta/cloudstorage/rackspace.py
test/test_slimta_cloudstorage.py
test/test_slimta_cloudstorage_aws.py
test/test_slimta_cloudstorage_rackspace_auth.py
test/test_slimta_cloudstorage_rackspace_files.py
test/test_slimta_cloudstorage_rackspace_queues.py