Metadata-Version: 1.1
Name: python-slimta-cloudstorage
Version: 0.1.1
Summary: Queue storage backend interfacing with cloud providers.
Home-page: http://slimta.org/
Author: Ian Good
Author-email: icgood@gmail.com
License: MIT
Platform: UNKNOWN
Classifier: Development Status :: 3 - Alpha
Classifier: Topic :: Communications :: Email :: Mail Transport Agents
Classifier: Intended Audience :: Developers
Classifier: Intended Audience :: Information Technology
Classifier: License :: OSI Approved :: MIT License
Classifier: Programming Language :: Python
